aiohttp_flashbag/__init__.py
aiohttp_flashbag-0.0.3.dist-info/METADATA
aiohttp_flashbag-0.0.3.dist-info/RECORD
aiohttp_flashbag-0.0.3.dist-info/WHEEL
aiohttp_flashbag-0.0.3.dist-info/top_level.txt
