Metadata-Version: 2.1
Name: aiohttp-flashbag
Version: 0.0.3
Summary: Flashbag (flash messages) support for aiohttp.web
Home-page: https://github.com/wikibusiness/aiohttp-flashbag
Author: Ocean S.A.
Author-email: osf@ocean.io
License: UNKNOWN
Keywords: flashbag,flash messages,aiohttp
Platform: UNKNOWN
Classifier: Development Status :: 5 - Production/Stable
Classifier: Intended Audience :: Developers
Classifier: License :: OSI Approved :: MIT License
Classifier: Operating System :: POSIX
Classifier: Operating System :: MacOS :: MacOS X
Classifier: Operating System :: Microsoft :: Windows
Classifier: Programming Language :: Python
Classifier: Programming Language :: Python :: 3
Classifier: Programming Language :: Python :: 3.5
Classifier: Programming Language :: Python :: 3.6
Requires-Dist: aiohttp (>=2.3.0)
Requires-Dist: aiohttp-session (>=1.2.0)
